battleship.v
module battleship (
  input            clk  ,
  input            rst  ,
  input            start,
  input      [1:0] X    ,
  input      [1:0] Y    ,
  input            pAb  ,
  input            pBb  ,
  output reg [7:0] disp0,
  output reg [7:0] disp1,
  output reg [7:0] disp2,
  output reg [7:0] disp3,
  output reg [7:0] led
);

reg[3:0]    state;
reg[15:0]   mapA;
reg[15:0]   mapB;
reg[2:0]    Score_A;
reg[2:0]    Score_B;
reg[1:0]    counter;
reg[2:0]    led_counter;
reg[1:0]    input_count;
reg         control;
reg         Z;
reg         SW0;
reg         SW1;
reg         SW2;
reg         SW3;

parameter LIMIT = 3;
parameter IDLE = 4'b0000;
parameter SHOW_A = 4'b0001;
parameter A_IN = 4'b0010;
parameter ERROR_A = 4'b0011;
parameter SHOW_B = 4'b0100;
parameter B_IN = 4'b0101;
parameter ERROR_B = 4'b0110;
parameter SHOW_SCORE = 4'b0111;
parameter A_SHOOT = 4'b1000;
parameter A_SINK = 4'b1001;
parameter A_WIN = 4'b1010;
parameter B_SHOOT = 4'b1011;
parameter B_SINK = 4'b1100;
parameter B_WIN = 4'b1101;
parameter zero = 2'b00;
parameter one = 2'b01;
parameter two = 2'b10;
parameter three = 2'b11;


always@(posedge clk or posedge rst) begin
  SW0 = Y[0];
  SW1 = Y[1];
  SW2 = X[0];
  SW3 = X[1];
end

always @(posedge clk or posedge rst) begin
  if(rst) begin
    state <= IDLE;
  end
  else begin
    case(state)
        IDLE:begin
          if(start) begin
             state <= SHOW_A;
          end
          else begin
            state <= IDLE;
          end
        end

        SHOW_A:begin 
          if (counter < LIMIT) begin
            state <= SHOW_A;
            counter <= counter + 1;
          end
          else begin
            state <= A_IN;
          end
        end
        A_IN: begin
          if(pAb) begin
            if(mapA[{Y,X}]) begin
              state <= ERROR_A;
            end
            else begin
              if(input_count > 2) begin
                state <= SHOW_B;
                mapA[{Y,X}] <= 1;
                input_count <= 0;
              end
              else begin
                state <= A_IN;
                mapA[{Y,X}] <= 1;
                input_count <= input_count+1;
              end
            end
          end
          else begin
            state <= A_IN;
          end
        end

        ERROR_A: begin
          if(counter < LIMIT) begin
            state <= ERROR_A;
            counter <= counter + 1;
          end
          else begin
            state <= A_IN;
          end
        end

        SHOW_B:begin
          if(counter < LIMIT) begin
            state <= SHOW_B;
            counter <= counter + 1;
          end
          else begin
            state <= B_IN;
          end
        end

        B_IN: begin
          if(pBb) begin
            if(mapB[{Y,X}]) begin
              state <= ERROR_B;
            end
            else begin
              if(input_count > 2) begin
                state <= SHOW_SCORE;
                mapB[{Y,X}] <= 1;
              end
              else begin
                state <= B_IN;
                mapB[{Y,X}] <= 1;
                input_count <= input_count + 1;
              end
            end
          end
          else begin
            state <= B_IN;
          end
        end

        ERROR_B: begin
          if(counter < LIMIT) begin
            state <= ERROR_B;
            counter <= counter + 1;
          end
          else begin
            state <= B_IN;
          end
        end

        SHOW_SCORE: begin
          if(counter < LIMIT) begin
            state <= SHOW_SCORE;
            counter <= counter + 1;
          end
          else begin 
            state <= A_SHOOT;
          end
        end

        A_SHOOT: begin
          if(pAb) begin
            if(mapB[{Y,X}]) begin
              state <= A_SINK;
              Score_A <= Score_A + 1;
              Z <= 1;
              mapB[{Y,X}] <= 0;
            end
            else begin
              state <= A_SINK;
              Score_A <= Score_A;
              Z <= 0;
            end
          end
          else begin
            state <= A_SHOOT;
          end
        end

        A_SINK: begin
          if(counter < LIMIT) begin
            counter <= counter + 1;
            if(Z) begin
              state <= A_SINK;
              led <= 8'b11111111;
            end
            else begin
              state <= A_SINK;
              led <= 8'b00000000;
            end
          end
          else begin
            if(Score_A > 3) begin
              state <= A_WIN;
            end
            else begin
              state <= B_SHOOT;
            end
          end
        end

        A_WIN: begin
          state <= A_WIN;
        end

        B_SHOOT:begin
          if(pBb) begin
            if(mapA[{Y,X}]) begin
              state <= B_SINK;
              Score_B <= Score_B + 1;
              Z <= 1;
              mapA[{Y,X}] <= 0;
            end
            else begin
              state <= B_SINK;
              Score_B <= Score_B;
              Z <= 0;
            end
          end
          else begin
            state <= B_SHOOT;
          end
        end

        B_SINK: begin
          if(counter < LIMIT) begin
            counter <= counter + 1;
            if(Z) begin
              state <= B_SINK;
              led <= 8'b11111111;
            end
            else begin
              state <= B_SINK;
              led <= 8'b00000000;
            end
          end
          else begin
            if(Score_B > 3) begin
              state <= B_WIN;
            end
            else begin
              state <= A_SHOOT;
            end
          end
        end

        B_WIN:begin
          state <= B_WIN;
        end

          
    endcase
  end

  end

  always@(posedge clk or posedge rst) begin
    if(rst) begin
      mapA <= 0;
      mapB <= 0;
      Score_A <= 0;
      Score_B <= 0;
      counter <= 0;
      input_count <= 0;
      led <= 8'b10011001;
      disp0 <= 8'b01111001;
      disp1 <= 8'b00111000;
      disp2 <= 8'b01011110;
      disp3 <= 8'b00000110;
      Z <= 0;
    end
    else begin
      case(state)

        IDLE: begin end
        SHOW_A: begin
          disp0 <= 0;
          disp1 <= 0;
          disp2 <= 0;
          disp3 <= 8'b01110111;
        end
        A_IN: begin
          disp3 <= 8'b00000000;
          disp2 <= 8'b00000000;
          if({SW3,SW2} == zero)begin
            disp1 <= 8'b00111111;
          end
          else if({SW3,SW2} == one)begin
            disp1 <= 8'b00000110;
          end
          else if({SW3,SW2} == two)begin
            disp1 <= 8'b01011011;
          end
          else begin
            disp1 <= 8'b01001111;
          end

          if({SW1,SW0} == zero)begin
            disp0 <= 8'b00111111;
          end
          else if({SW1,SW0} == one)begin
            disp0 <= 8'b00000110;
          end
          else if({SW1,SW0} == two)begin
            disp0 <= 8'b01011011;
          end
          else begin
            disp0 <= 8'b01001111;
          end
          led <= 8'b10000000;
          led[5:4] <= input_count;
          counter <= 0;
        end
        
        ERROR_A: begin
          disp0 <= 8'b01011100;
          disp1 <= 8'b01010000;
          disp2 <= 8'b01010000;
          disp3 <= 8'b01111001;
          led <= 8'b10011001;
        end
        
        SHOW_B: begin 
          disp3 <= 8'b01111100;
          disp2 <= 0;
          disp1 <= 0;
          disp0 <= 0;
          led <= 8'b10011001;
        end
        
        B_IN: begin
          disp3 <= 8'b00000000;
          disp2 <= 8'b00000000;
          if({SW3,SW2} == zero)begin
            disp1 <= 8'b00111111;
          end
          else if({SW3,SW2} == one)begin
            disp1 <= 8'b00000110;
          end
          else if({SW3,SW2} == two)begin
            disp1 <= 8'b01011011;
          end
          else begin
            disp1 <= 8'b01001111;
          end

          if({SW1,SW0} == zero)begin
            disp0 <= 8'b00111111;
          end
          else if({SW1,SW0} == one)begin
            disp0 <= 8'b00000110;
          end
          else if({SW1,SW0} == two)begin
            disp0 <= 8'b01011011;
          end
          else begin
            disp0 <= 8'b01001111;
          end
          led <= 8'b00000001;
          led[3:2] <= input_count;
          counter <= 0;
        end
        
        ERROR_B:begin
          disp0 <= 8'b01011100;
          disp1 <= 8'b01010000;
          disp2 <= 8'b01010000;
          disp3 <= 8'b01111001;
          led <= 8'b10011001;
        end

        SHOW_SCORE: begin
          disp3 <= 0;
          disp2 <= 8'b00111111;
          disp1 <= 8'b01000000;
          disp0 <= 8'b00111111;
          led <= 8'b10011001;
        end
        A_SHOOT: begin
          disp3 <= 8'b00000000;
          disp2 <= 8'b00000000;
          if({SW3,SW2} == zero)begin
            disp1 <= 8'b00111111;
          end
          else if({SW3,SW2} == one)begin
            disp1 <= 8'b00000110;
          end
          else if({SW3,SW2} == two)begin
            disp1 <= 8'b01011011;
          end
          else begin
            disp1 <= 8'b01001111;
          end

          if({SW1,SW0} == zero)begin
            disp0 <= 8'b00111111;
          end
          else if({SW1,SW0} == one)begin
            disp0 <= 8'b00000110;
          end
          else if({SW1,SW0} == two)begin
            disp0 <= 8'b01011011;
          end
          else begin
            disp0 <= 8'b01001111;
          end
          led <= 8'b10000000;
          led[5:4] <= Score_A;
          led[3:2] <= Score_B;
          counter <= 0;
        end

        A_SINK: begin
          if(Score_A == zero)begin
            disp2 <= 8'b00111111;
          end
          else if(Score_A == one)begin
            disp2 <= 8'b00000110;
          end
          else if(Score_A == two)begin
            disp2 <= 8'b01011011;
          end
          else if(Score_A == three)begin
            disp2 <= 8'b01001111;
          end
          else begin
            disp2 <= 8'b01100110;
          end
          disp1 <= 8'b01000000;
          if(Score_B == zero)begin
            disp0 <= 8'b00111111;
          end
          else if(Score_B == one)begin
            disp0 <= 8'b00000110;
          end
          else if(Score_B == two)begin
            disp0 <= 8'b01011011;
          end
          else if(Score_B == three)begin
            disp0 <= 8'b01001111;
          end
          else begin
            disp0 <= 8'b01100110;
          end
        end

        A_WIN: begin
          disp3 <= 8'b01110111;
          if(Score_A == zero)begin
            disp2 <= 8'b00111111;
          end
          else if(Score_A == one)begin
            disp2 <= 8'b00000110;
          end
          else if(Score_A == two)begin
            disp2 <= 8'b01011011;
          end
          else if(Score_A == three)begin
            disp2 <= 8'b01001111;
          end
          else begin
            disp2 <= 8'b01100110;
          end
          disp1 <= 8'b01000000;
          if(Score_B == zero)begin
            disp0 <= 8'b00111111;
          end
          else if(Score_B == one)begin
            disp0 <= 8'b00000110;
          end
          else if(Score_B == two)begin
            disp0 <= 8'b01011011;
          end
          else if(Score_B == three)begin
            disp0 <= 8'b01001111;
          end
          else begin
            disp0 <= 8'b01100110;
          end
        end

        B_SHOOT: begin
          disp3 <= 8'b00000000;
          disp2 <= 8'b00000000;
          if({SW3,SW2} == zero)begin
            disp1 <= 8'b00111111;
          end
          else if({SW3,SW2} == one)begin
            disp1 <= 8'b00000110;
          end
          else if({SW3,SW2} == two)begin
            disp1 <= 8'b01011011;
          end
          else begin
            disp1 <= 8'b01001111;
          end

          if({SW1,SW0} == zero)begin
            disp0 <= 8'b00111111;
          end
          else if({SW1,SW0} == one)begin
            disp0 <= 8'b00000110;
          end
          else if({SW1,SW0} == two)begin
            disp0 <= 8'b01011011;
          end
          else begin
            disp0 <= 8'b01001111;
          end
          led <= 8'b00000001;
          led[5:4] <= Score_A;
          led[3:2] <= Score_B;
          counter <= 0;
        end

        B_SINK: begin
          if(Score_A == zero)begin
            disp2 <= 8'b00111111;
          end
          else if(Score_A == one)begin
            disp2 <= 8'b00000110;
          end
          else if(Score_A == two)begin
            disp2 <= 8'b01011011;
          end
          else if(Score_A == three)begin
            disp2 <= 8'b01001111;
          end
          else begin
            disp2 <= 8'b01100110;
          end
          disp1 <= 8'b01000000;
          if(Score_B == zero)begin
            disp0 <= 8'b00111111;
          end
          else if(Score_B == one)begin
            disp0 <= 8'b00000110;
          end
          else if(Score_B == two)begin
            disp0 <= 8'b01011011;
          end
          else if(Score_B == three)begin
            disp0 <= 8'b01001111;
          end
          else begin
            disp0 <= 8'b01100110;
          end
        end

        B_WIN: begin
          disp3 <= 8'b01111100;
          if(Score_A == zero) begin
            disp2 <= 8'b00111111;
          end
          else if(Score_A == one) begin
            disp2 <= 8'b00000110;
          end
          else if(Score_A == two)begin
            disp2 <= 8'b01011011;
          end
          else if(Score_A == three)begin
            disp2 <= 8'b01001111;
          end
          else begin
            disp2 <= 8'b01100110;
          end
          disp1 <= 8'b01000000;
          if(Score_B == zero) begin
            disp0 <= 8'b00111111;
          end
          else if(Score_B == one)begin
            disp0 <= 8'b00000110;
          end
          else if(Score_B == two)begin
            disp0 <= 8'b01011011;
          end
          else if(Score_B == three)begin
            disp0 <= 8'b01001111;
          end
          else begin
            disp0 <= 8'b01100110;
          end
        end

      endcase
    end
  end

  always @(posedge clk or posedge rst) begin
    if(rst) begin
      led_counter <= 0;
      led <= 0;
    end
    else if((state == A_WIN) || (state == B_WIN)) begin
      if(led_counter < LIMIT) begin
        led <= 8'b11111111;
        led_counter <= led_counter + 1;
      end
      else if (led_counter < 2*LIMIT)begin
        led <= 0;
        led_counter <= led_counter + 1;
        if(led_counter == 5) begin
          led_counter <= 0;
        end
      end
    end
  end


endmodule

battleship_tb.v
// DO NOT MODIFY THE MODULE NAMES, SIGNAL NAMES, SIGNAL PROPERTIES
module battleship_tb();

  reg clk;
  reg rst;
  reg start;
  reg [1:0] X;
  reg [1:0] Y;
  reg pAb;
  reg pBb;
  wire [7:0] disp0;
  wire [7:0] disp1;
  wire [7:0] disp2;
  wire [7:0] disp3;
  wire [7:0] led;

  battleship  ba00 (
    .clk(clk),
    .rst(rst),
    .start(start),
    .X(X),
    .Y(Y),
    .pAb(pAb),
    .pBb(pBb),
    .disp0(disp0),
    .disp1(disp1),
    .disp2(disp2),
    .disp3(disp3),
    .led(led)
  );
  parameter HP = 5;
  parameter FP = (2*HP);

always #HP  clk = ~clk ;

initial begin
    //  * Our waveform is saved under this file.
    
    $dumpfile("battleship_tb.vcd"); 
    
    // * Get the variables from the module.

    $dumpvars(0,battleship_tb);

    $display("Simulation started.");
    clk = 1;
    rst = 1;
    start = 0;
    X = 0;
    Y = 0;
    pAb = 0;
    pBb = 0;
    #FP;

    rst = 0;
    #FP;

    start = 1;
    #(2*FP);

    start = 0;
    #FP;

    rst = 0;
    X = 2'b00;
    Y = 2'b00;
    pAb = 0;
    pBb = 0;
    #(5*FP);

    rst = 0;
    X = 2'b00;
    Y = 2'b00;
    pAb = 1;
    pBb = 0;
    #FP;

    rst = 0;
    X = 2'b00;
    Y = 2'b01;
    pAb = 1;
    pBb = 0;
    #FP;

    rst = 0;
    X = 2'b01;
    Y = 2'b00;
    pAb = 1;
    pBb = 0;
    #FP;

    rst = 0;
    X = 2'b01;
    Y = 2'b01;
    pAb = 1;
    pBb = 0;
    #FP;

    rst = 0;
    X = 2'b00;
    Y = 2'b00;
    pAb = 0;
    pBb = 0;
    #(5*FP);

    rst = 0;
    X = 2'b00;
    Y = 2'b00;
    pAb = 0;
    pBb = 1;
    #FP;

    rst = 0;
    X = 2'b00;
    Y = 2'b01;
    pAb = 0;
    pBb = 1;
    #FP;

    rst = 0;
    X = 2'b01;
    Y = 2'b00;
    pAb = 0;
    pBb = 1;
    #FP;   
    
    rst = 0;
    X = 2'b01;
    Y = 2'b01;
    pAb = 0;
    pBb = 1;
    #FP;

    rst = 0;
    X = 2'b00;
    Y = 2'b00;
    pAb = 0;
    pBb = 0;
    #(5*FP);

    rst = 0;
    X = 2'b00;
    Y = 2'b00;
    pAb = 1;
    pBb = 0;
    #FP;


    rst = 0;
    X = 2'b00;
    Y = 2'b00;
    pAb = 0;
    pBb = 0;
    #(5*FP);

    rst = 0;
    X = 2'b00;
    Y = 2'b00;
    pAb = 0;
    pBb = 1;
    #FP;

    rst = 0;
    X = 2'b00;
    Y = 2'b00;
    pAb = 0;
    pBb = 0;
    #(5*FP);

    rst = 0;
    X = 2'b00;
    Y = 2'b01;
    pAb = 1;
    pBb = 0;
    #FP;

  
    rst = 0;
    X = 2'b00;
    Y = 2'b00;
    pAb = 0;
    pBb = 0;
    #(5*FP);

    rst = 0;
    X = 2'b00;
    Y = 2'b01;
    pAb = 0;
    pBb = 1;
    #FP;

    
      rst = 0;
    X = 2'b00;
    Y = 2'b00;
    pAb = 0;
    pBb = 0;
    #(5*FP);

    rst = 0;
    X = 2'b11;
    Y = 2'b11;
    pAb = 1;
    pBb = 0;
    #FP;

    rst = 0;
    X = 2'b00;
    Y = 2'b00;
    pAb = 0;
    pBb = 0;
    #(5*FP);
    
    rst = 0;
    X = 2'b01;
    Y = 2'b00;
    pAb = 0;
    pBb = 1;
    #FP;

    
    rst = 0;
    X = 2'b00;
    Y = 2'b00;
    pAb = 0;
    pBb = 0;
    #(5*FP);

    rst = 0;
    X = 2'b01;
    Y = 2'b01;
    pAb = 1;
    pBb = 0;
    #FP;

    rst = 0;
    X = 2'b00;
    Y = 2'b00;
    pAb = 0;
    pBb = 0;
    #(5*FP);

    rst = 0;
    X = 2'b01;
    Y = 2'b01;
    pAb = 0;
    pBb = 1;
    #FP;

    rst = 0;
    X = 2'b00;
    Y = 2'b00;
    pAb = 0;
    pBb = 0;
    #(15*FP);

    $display("Simulation finished.");
    $finish(); // Finish simulation.
end

endmodule

battleship_tb.vcd
$date
	Mon Dec 23 15:39:21 2024
$end
$version
	Icarus Verilog
$end
$timescale
	1s
$end
$scope module battleship_tb $end
$var wire 8 ! led [7:0] $end
$var wire 8 " disp3 [7:0] $end
$var wire 8 # disp2 [7:0] $end
$var wire 8 $ disp1 [7:0] $end
$var wire 8 % disp0 [7:0] $end
$var parameter 64 & FP $end
$var parameter 32 ' HP $end
$var reg 2 ( X [1:0] $end
$var reg 2 ) Y [1:0] $end
$var reg 1 * clk $end
$var reg 1 + pAb $end
$var reg 1 , pBb $end
$var reg 1 - rst $end
$var reg 1 . start $end
$scope module ba00 $end
$var wire 2 / X [1:0] $end
$var wire 2 0 Y [1:0] $end
$var wire 1 * clk $end
$var wire 1 + pAb $end
$var wire 1 , pBb $end
$var wire 1 - rst $end
$var wire 1 . start $end
$var parameter 4 1 A_IN $end
$var parameter 4 2 A_SHOOT $end
$var parameter 4 3 A_SINK $end
$var parameter 4 4 A_WIN $end
$var parameter 4 5 B_IN $end
$var parameter 4 6 B_SHOOT $end
$var parameter 4 7 B_SINK $end
$var parameter 4 8 B_WIN $end
$var parameter 4 9 ERROR_A $end
$var parameter 4 : ERROR_B $end
$var parameter 4 ; IDLE $end
$var parameter 32 < LIMIT $end
$var parameter 4 = SHOW_A $end
$var parameter 4 > SHOW_B $end
$var parameter 4 ? SHOW_SCORE $end
$var parameter 2 @ one $end
$var parameter 2 A three $end
$var parameter 2 B two $end
$var parameter 2 C zero $end
$var reg 1 D SW0 $end
$var reg 1 E SW1 $end
$var reg 1 F SW2 $end
$var reg 1 G SW3 $end
$var reg 3 H Score_A [2:0] $end
$var reg 3 I Score_B [2:0] $end
$var reg 1 J Z $end
$var reg 2 K counter [1:0] $end
$var reg 8 L disp0 [7:0] $end
$var reg 8 M disp1 [7:0] $end
$var reg 8 N disp2 [7:0] $end
$var reg 8 O disp3 [7:0] $end
$var reg 2 P input_count [1:0] $end
$var reg 8 Q led [7:0] $end
$var reg 3 R led_counter [2:0] $end
$var reg 16 S mapA [15:0] $end
$var reg 16 T mapB [15:0] $end
$var reg 4 U state [3:0] $end
$upscope $end
$upscope $end
$enddefinitions $end
$comment Show the parameter values. $end
$dumpall
b0 C
b10 B
b11 A
b1 @
b111 ?
b100 >
b1 =
b11 <
b0 ;
b110 :
b11 9
b1101 8
b1100 7
b1011 6
b101 5
b1010 4
b1001 3
b1000 2
b10 1
b101 '
b1010 &
$end
#0
$dumpvars
b0 U
b0 T
b0 S
b0 R
b10011001 Q
b0 P
b110 O
b1011110 N
b111000 M
b1111001 L
b0 K
0J
b0 I
b0 H
0G
0F
0E
0D
b0 0
b0 /
0.
1-
0,
0+
1*
b0 )
b0 (
b1111001 %
b111000 $
b1011110 #
b110 "
b10011001 !
$end
#5
0*
#10
1*
0-
#15
0*
#20
b1 U
1*
1.
#25
0*
#30
b1110111 "
b1110111 O
b0 #
b0 N
b0 $
b0 M
b0 %
b0 L
b1 K
1*
#35
0*
#40
b10 K
1*
0.
#45
0*
#50
b11 K
1*
#55
0*
#60
b10 U
1*
#65
0*
#70
b0 K
b10000000 !
b10000000 Q
b111111 %
b111111 L
b111111 $
b111111 M
b0 "
b0 O
1*
#75
0*
#80
1*
#85
0*
#90
1*
#95
0*
#100
b1 P
b1 S
1*
1+
#105
0*
#110
b10010000 !
b10010000 Q
b110 %
b110 L
b10 P
b10001 S
1D
1*
b1 )
b1 0
#115
0*
#120
b11 P
b10011 S
b10100000 !
b10100000 Q
1F
0D
1*
b0 )
b0 0
b1 (
b1 /
#125
0*
#130
b10110000 !
b10110000 Q
b110 $
b110 M
b0 P
b110011 S
b100 U
1D
1*
b1 )
b1 0
#135
0*
#140
b1 K
b10011001 !
b10011001 Q
b0 %
b0 L
b0 $
b0 M
b1111100 "
b1111100 O
0F
0D
1*
0+
b0 )
b0 0
b0 (
b0 /
#145
0*
#150
b10 K
1*
#155
0*
#160
b11 K
1*
#165
0*
#170
b101 U
1*
#175
0*
#180
b0 K
b1 !
b1 Q
b111111 %
b111111 L
b111111 $
b111111 M
b0 "
b0 O
1*
#185
0*
#190
b1 P
b1 T
1*
1,
#195
0*
#200
b10 P
b10001 T
b101 !
b101 Q
1D
1*
b1 )
b1 0
#205
0*
#210
b1001 !
b1001 Q
b110 $
b110 M
b11 P
b10011 T
1F
0D
1*
b0 )
b0 0
b1 (
b1 /
#215
0*
#220
b110011 T
b111 U
b1101 !
b1101 Q
1D
1*
b1 )
b1 0
#225
0*
#230
b10011001 !
b10011001 Q
b1000000 $
b1000000 M
b111111 #
b111111 N
b1 K
0F
0D
1*
0,
b0 )
b0 0
b0 (
b0 /
#235
0*
#240
b10 K
1*
#245
0*
#250
b11 K
1*
#255
0*
#260
b1000 U
1*
#265
0*
#270
b0 K
b10000000 !
b10000000 Q
b111111 $
b111111 M
b0 #
b0 N
1*
#275
0*
#280
b110010 T
1J
b1 H
b1001 U
1*
1+
#285
0*
#290
b1000000 $
b1000000 M
b110 #
b110 N
b11111111 !
b11111111 Q
b1 K
1*
0+
#295
0*
#300
b10 K
1*
#305
0*
#310
b11 K
1*
#315
0*
#320
b1011 U
1*
#325
0*
#330
b0 K
b10001 !
b10001 Q
b111111 $
b111111 M
b0 #
b0 N
1*
#335
0*
#340
b110010 S
b1 I
b1100 U
b10001 !
b10001 Q
1*
1,
#345
0*
#350
b110 %
b110 L
b1000000 $
b1000000 M
b110 #
b110 N
b11111111 !
b11111111 Q
b1 K
1*
0,
#355
0*
#360
b10 K
1*
#365
0*
#370
b11 K
1*
#375
0*
#380
b1000 U
1*
#385
0*
#390
b0 K
b10010100 !
b10010100 Q
b111111 %
b111111 L
b111111 $
b111111 M
b0 #
b0 N
1*
#395
0*
#400
b100010 T
b10 H
b1001 U
b10010100 !
b10010100 Q
1D
1*
1+
b1 )
b1 0
#405
0*
#410
b110 %
b110 L
b1000000 $
b1000000 M
b1011011 #
b1011011 N
b11111111 !
b11111111 Q
b1 K
0D
1*
0+
b0 )
b0 0
#415
0*
#420
b10 K
1*
#425
0*
#430
b11 K
1*
#435
0*
#440
b1011 U
1*
#445
0*
#450
b0 K
b100101 !
b100101 Q
b111111 %
b111111 L
b111111 $
b111111 M
b0 #
b0 N
1*
#455
0*
#460
b100010 S
b10 I
b1100 U
b100101 !
b100101 Q
1D
1*
1,
b1 )
b1 0
#465
0*
#470
b1011011 %
b1011011 L
b1000000 $
b1000000 M
b1011011 #
b1011011 N
b11111111 !
b11111111 Q
b1 K
0D
1*
0,
b0 )
b0 0
#475
0*
#480
b10 K
1*
#485
0*
#490
b11 K
1*
#495
0*
#500
b1000 U
1*
#505
0*
#510
b0 K
b10101000 !
b10101000 Q
b111111 %
b111111 L
b111111 $
b111111 M
b0 #
b0 N
1*
#515
0*
#520
0J
b1001 U
b10101000 !
b10101000 Q
1G
1F
1E
1D
1*
1+
b11 )
b11 0
b11 (
b11 /
#525
0*
#530
b1011011 %
b1011011 L
b1000000 $
b1000000 M
b1011011 #
b1011011 N
b0 !
b0 Q
b1 K
0G
0F
0E
0D
1*
0+
b0 )
b0 0
b0 (
b0 /
#535
0*
#540
b10 K
1*
#545
0*
#550
b11 K
1*
#555
0*
#560
b1011 U
1*
#565
0*
#570
b0 K
b101001 !
b101001 Q
b111111 %
b111111 L
b111111 $
b111111 M
b0 #
b0 N
1*
#575
0*
#580
b100000 S
1J
b11 I
b1100 U
b101001 !
b101001 Q
1F
1*
1,
b1 (
b1 /
#585
0*
#590
b1001111 %
b1001111 L
b1000000 $
b1000000 M
b1011011 #
b1011011 N
b11111111 !
b11111111 Q
b1 K
0F
1*
0,
b0 (
b0 /
#595
0*
#600
b10 K
1*
#605
0*
#610
b11 K
1*
#615
0*
#620
b1000 U
1*
#625
0*
#630
b0 K
b10101100 !
b10101100 Q
b111111 %
b111111 L
b111111 $
b111111 M
b0 #
b0 N
1*
#635
0*
#640
b10 T
b11 H
b1001 U
b10101100 !
b10101100 Q
1F
1D
1*
1+
b1 )
b1 0
b1 (
b1 /
#645
0*
#650
b1001111 %
b1001111 L
b1000000 $
b1000000 M
b1001111 #
b1001111 N
b11111111 !
b11111111 Q
b1 K
0F
0D
1*
0+
b0 )
b0 0
b0 (
b0 /
#655
0*
#660
b10 K
1*
#665
0*
#670
b11 K
1*
#675
0*
#680
b1011 U
1*
#685
0*
#690
b0 K
b111101 !
b111101 Q
b111111 %
b111111 L
b111111 $
b111111 M
b0 #
b0 N
1*
#695
0*
#700
b0 S
b100 I
b1100 U
b111101 !
b111101 Q
1F
1D
1*
1,
b1 )
b1 0
b1 (
b1 /
#705
0*
#710
b1100110 %
b1100110 L
b1000000 $
b1000000 M
b1001111 #
b1001111 N
b11111111 !
b11111111 Q
b1 K
0F
0D
1*
0,
b0 )
b0 0
b0 (
b0 /
#715
0*
#720
b10 K
1*
#725
0*
#730
b11 K
1*
#735
0*
#740
b1101 U
1*
#745
0*
#750
b1 R
b1111100 "
b1111100 O
1*
#755
0*
#760
b10 R
1*
#765
0*
#770
b11 R
1*
#775
0*
#780
b100 R
b0 !
b0 Q
1*
#785
0*
#790
b101 R
1*
#795
0*
#800
b0 R
1*
#805
0*
#810
b1 R
b11111111 !
b11111111 Q
1*
#815
0*
#820
b10 R
1*
#825
0*
#830
b11 R
1*
#835
0*
#840
b100 R
b0 !
b0 Q
1*
#845
0*
#850
b101 R
1*
#855
0*
#860
b0 R
1*
